ohHtmlToMarkdown.py
ohHtmlToMarkdown-1.0.0.dist-info/METADATA
ohHtmlToMarkdown-1.0.0.dist-info/RECORD
ohHtmlToMarkdown-1.0.0.dist-info/WHEEL
ohHtmlToMarkdown-1.0.0.dist-info/top_level.txt
