Metadata-Version: 2.1
Name: ohHtmlToMarkdown
Version: 1.0.0
Summary: A Python Library for converting HTML to Markdown.
Home-page: https://github.com/wfgydbu/ohHTML2Markdown
Author: Ethan Huang
Author-email: wfgydbu@163.com
License: GNU GPL 3
Platform: UNKNOWN
Classifier: Development Status :: 5 - Production/Stable
Classifier: Intended Audience :: Developers
Classifier: License :: OSI Approved :: GNU General Public License (GPL)
Classifier: Programming Language :: Python :: 3.6
Classifier: Operating System :: OS Independent
Requires-Dist: beautifulsoup4 (==4.6.0)
